thorod/__about__.py
thorod/__init__.py
thorod/__main__.py
thorod/bencode.py
thorod/cli.py
thorod/commands.py
thorod/config.py
thorod/constants.py
thorod/core.py
thorod/output.py
thorod/utils.py
thorod-2.1.0.dist-info/entry_points.txt
thorod-2.1.0.dist-info/LICENSE
thorod-2.1.0.dist-info/WHEEL
thorod-2.1.0.dist-info/METADATA
thorod-2.1.0.dist-info/RECORD
