Metadata-Version: 2.1
Name: thorod
Version: 2.1.0
Summary: A CLI utility for torrent creation and manipulation.
Home-page: https://github.com/thebigmunch/thorod
License: MIT
Author: thebigmunch
Author-email: mail@thebigmunch.me
Requires-Python: >=3.6,<4.0
Classifier: License :: OSI Approved :: MIT License
Classifier: Programming Language :: Python :: 3
Classifier: Programming Language :: Python :: 3.6
Classifier: Programming Language :: Python :: 3.7
Classifier: Programming Language :: Python :: 3.8
Provides-Extra: dev
Provides-Extra: doc
Provides-Extra: lint
Requires-Dist: appdirs (>=1.4,<2.0)
Requires-Dist: attrs (>=18.2,<19.4)
Requires-Dist: colorama (<1.0.0)
Requires-Dist: flake8 (>=3.5,<4.0); extra == "dev" or extra == "lint"
Requires-Dist: flake8-builtins (>=1.0,<2.0); extra == "dev" or extra == "lint"
Requires-Dist: flake8-comprehensions (>=2.0,<=4.0); extra == "dev" or extra == "lint"
Requires-Dist: flake8-import-order (>=0.18,<0.19); extra == "dev" or extra == "lint"
Requires-Dist: flake8-import-order-tbm (>=1.0,<2.0); extra == "dev" or extra == "lint"
Requires-Dist: nox (>=2019,<2020); extra == "dev"
Requires-Dist: pendulum (>=2.0,<=3.0,!=2.0.5,!=2.1.0)
Requires-Dist: pprintpp (<1.0.0)
Requires-Dist: rich (>=0.8)
Requires-Dist: sortedcontainers (>=2.0,<3.0)
Requires-Dist: sphinx (>=2.0,<3.0); extra == "dev" or extra == "doc"
Requires-Dist: sphinx-argparse (>=0.2,<0.3); extra == "dev" or extra == "doc"
Requires-Dist: sphinx-material (<1.0.0); extra == "dev" or extra == "doc"
Requires-Dist: tbm-utils (>=2.4,<3.0)
Requires-Dist: tomlkit (>=0.5,<0.6)
Project-URL: Repository, https://github.com/thebigmunch/thorod
